gaia_sdk/__init__.py
gaia_sdk/api/ByteBuffer.py
gaia_sdk/api/GaiaCredentials.py
gaia_sdk/api/ISensorFunction.py
gaia_sdk/api/ISensorStream.py
gaia_sdk/api/IdentityOp.py
gaia_sdk/api/SkillRef.py
gaia_sdk/api/VariableRegistry.py
gaia_sdk/api/__init__.py
gaia_sdk/api/client_options.py
gaia_sdk/api/crypto.py
gaia_sdk/api/data/DataRef.py
gaia_sdk/api/data/DataRefRequestConfig.py
gaia_sdk/api/data/DataUpload.py
gaia_sdk/api/data/DataUploadContent.py
gaia_sdk/api/data/__init__.py
gaia_sdk/api/rx/rx.py
gaia_sdk/api/transporter/__init__.py
gaia_sdk/api/transporter/abstract_transporter.py
gaia_sdk/gaia.py
gaia_sdk/graphql/GaiaClient.py
gaia_sdk/graphql/GaiaClientBuilder.py
gaia_sdk/graphql/GaiaClientFactory.py
gaia_sdk/graphql/GaiaRequest.py
gaia_sdk/graphql/GaiaResponse.py
gaia_sdk/graphql/GaiaScalars.py
gaia_sdk/graphql/__init__.py
gaia_sdk/graphql/request/enumeration/EdgeOrderByField.py
gaia_sdk/graphql/request/enumeration/EdgeType.py
gaia_sdk/graphql/request/enumeration/Order.py
gaia_sdk/graphql/request/enumeration/OrderByField.py
gaia_sdk/graphql/request/input/CancelSkillBuildJobImpulse.py
gaia_sdk/graphql/request/input/ConnectAppendNodeImpulse.py
gaia_sdk/graphql/request/input/ConnectRemoveNodeImpulse.py
gaia_sdk/graphql/request/input/ConnectSetNodeImpulse.py
gaia_sdk/graphql/request/input/ConnectUnsetNodeImpulse.py
gaia_sdk/graphql/request/input/CreateApiKeyImpulse.py
gaia_sdk/graphql/request/input/CreateBehaviourImpulse.py
gaia_sdk/graphql/request/input/CreateCodeImpulse.py
gaia_sdk/graphql/request/input/CreateEdgeImpulse.py
gaia_sdk/graphql/request/input/CreateFulfilmentImpulse.py
gaia_sdk/graphql/request/input/CreateIdentityImpulse.py
gaia_sdk/graphql/request/input/CreateIntentImpulse.py
gaia_sdk/graphql/request/input/CreatePromptImpulse.py
gaia_sdk/graphql/request/input/CreateRoleImpulse.py
gaia_sdk/graphql/request/input/CreateSkillBuildJobImpulse.py
gaia_sdk/graphql/request/input/CreateSkillImpulse.py
gaia_sdk/graphql/request/input/CreateSkillProvisionImpulse.py
gaia_sdk-4.2.0.dist-info/entry_points.txt
gaia_sdk-4.2.0.dist-info/WHEEL
gaia_sdk-4.2.0.dist-info/METADATA
gaia_sdk-4.2.0.dist-info/RECORD
