Metadata-Version: 2.1
Name: gaia-sdk
Version: 4.2.0
Summary: Python SDK for the GAIA ecosystem.
Author: Leftshift One
Author-email: contact@leftshift.one
Requires-Python: >=3.6,<4.0
Classifier: Programming Language :: Python :: 3
Classifier: Programming Language :: Python :: 3.6
Classifier: Programming Language :: Python :: 3.7
Classifier: Programming Language :: Python :: 3.8
Requires-Dist: Rx (>=3.1.1,<4.0.0)
Requires-Dist: requests (>=2.27.0,<3.0.0)
